deployfish/__init__.py
deployfish/exceptions.py
deployfish/main.py
deployfish/py.typed
deployfish/registry.py
deployfish/types.py
deployfish/config/__init__.py
deployfish/config/config.py
deployfish/config/processors/__init__.py
deployfish/config/processors/abstract.py
deployfish/config/processors/environment.py
deployfish/config/processors/terraform.py
deployfish/config/test/__init__.py
deployfish/config/test/env_file.env
deployfish/config/test/interpolate.yml
deployfish/config/test/terraform.tfstate
deployfish/config/test/terraform.tfstate.0.12
deployfish/config/test/terraform.tfstate.prod
deployfish/config/test/terraform.tfstate.qa
deployfish/config/test/terraform_interpolate.yml
deployfish/config/test/test_Config.py
deployfish/config/test/test_Terraform.py
deployfish/controllers/__init__.py
deployfish/controllers/base.py
deployfish/controllers/cluster.py
deployfish/controllers/commands.py
deployfish/controllers/crud.py
deployfish/controllers/elb.py
deployfish/controllers/elbv2.py
deployfish/controllers/invoked_task.py
deployfish/controllers/logs.py
deployfish/controllers/network.py
deployfish/controllers/rds.py
deployfish/controllers/secrets.py
deployfish/controllers/service.py
deployfish/controllers/task.py
deployfish/controllers/tunnel.py
deployfish/controllers/utils.py
deployfish/controllers/.mypy_cache/.gitignore
deployfish/controllers/.mypy_cache/CACHEDIR.TAG
deployfish/controllers/.mypy_cache/3.11/@plugins_snapshot.json
deployfish/controllers/.mypy_cache/3.11/_ast.data.json
deployfish/controllers/.mypy_cache/3.11/_ast.meta.json
deployfish/controllers/.mypy_cache/3.11/_codecs.data.json
deployfish/controllers/.mypy_cache/3.11/_codecs.meta.json
deployfish/controllers/.mypy_cache/3.11/_collections_abc.data.json
deployfish/controllers/.mypy_cache/3.11/_collections_abc.meta.json
deployfish/controllers/.mypy_cache/3.11/_compression.data.json
deployfish/controllers/.mypy_cache/3.11/_compression.meta.json
deployfish/controllers/.mypy_cache/3.11/_decimal.data.json
deployfish-1.15.2.dist-info/licenses/AUTHORS.txt
deployfish-1.15.2.dist-info/licenses/LICENSE.txt
deployfish-1.15.2.dist-info/METADATA
deployfish-1.15.2.dist-info/WHEEL
deployfish-1.15.2.dist-info/entry_points.txt
deployfish-1.15.2.dist-info/top_level.txt
deployfish-1.15.2.dist-info/RECORD
